{
  "critical": [],
  "high": [],
  "medium": [
    {
      "module": "attendance",
      "test": "Frontend CRUD - Control de Asistencia",
      "error": "7 tests fallaron",
      "context": {
        "errors": [
          {
            "test": "Add Button",
            "error": "Botón \"Agregar Control de Asistencia\" no funciona",
            "suggestion": "Verificar onclick=\"openAddattendanceModal()\" en el HTML"
          },
          {
            "test": "CRUD - Create",
            "error": "SyntaxError: Failed to execute 'querySelector' on 'Document': 'button:contains(\"Agregar\"), button[onclick*=\"Add\"], button[onclick*=\"add\"]' is not a valid selector.",
            "suggestion": "Revisar consola del navegador para ver errores JavaScript"
          },
          {
            "test": "CRUD - Read",
            "error": "Registro con ID undefined no encontrado en la lista",
            "suggestion": "Verificar que la función loadattendance() esté poblando la tabla correctamente"
          },
          {
            "test": "CRUD - Update",
            "error": "No se encontró botón de editar",
            "suggestion": "Agregar botón con onclick=\"editattendance(id)\""
          },
          {
            "test": "CRUD - Delete",
            "error": "No se encontró botón de eliminar",
            "suggestion": "Agregar botón con onclick=\"deleteattendance(id)\""
          },
          {
            "test": "Row Buttons",
            "error": "No se encontraron botones de acción (Editar/Eliminar)",
            "suggestion": "Agregar botones en la columna de acciones con onclick=\"editattendance(id)\" y onclick=\"deleteattendance(id)\""
          },
          {
            "test": "Console Errors",
            "error": "1 errores críticos de consola detectados",
            "suggestion": "Revisar errores en consola del navegador al cargar Control de Asistencia"
          }
        ],
        "http_errors": [],
        "console_errors": [
          {
            "type": "console",
            "message": "Failed to load resource: the server responded with a status of 404 (Not Found)",
            "timestamp": "2025-10-25T16:04:07.716Z"
          }
        ],
        "network_errors": []
      },
      "logId": "6ed431a4-50c7-4fef-bfec-91f39624bfe7",
      "severity": "medium"
    }
  ],
  "low": [
    {
      "module": "employee-map",
      "test": "Frontend CRUD - Mapa de Empleados",
      "error": "Módulo no está implementado o no carga correctamente",
      "context": null,
      "logId": "f8f15c68-c4e7-49f3-a4ea-ace8ff3705c5",
      "severity": "low"
    },
    {
      "module": "art-management",
      "test": "Frontend CRUD - Gestión de ART",
      "error": "Módulo no está implementado o no carga correctamente",
      "context": null,
      "logId": "f3710518-9120-43a9-a9ac-de81c82b0bb3",
      "severity": "low"
    },
    {
      "module": "departments",
      "test": "Frontend CRUD - Departamentos",
      "error": "Módulo no está implementado o no carga correctamente",
      "context": null,
      "logId": "f1d0fa56-c055-470d-b8a0-82f111c5357d",
      "severity": "low"
    },
    {
      "module": "training-management",
      "test": "Frontend CRUD - Gestión de Capacitaciones",
      "error": "Módulo no está implementado o no carga correctamente",
      "context": null,
      "logId": "ed7779e4-35a5-4071-a970-0e8612a23835",
      "severity": "low"
    },
    {
      "module": "job-postings",
      "test": "Frontend CRUD - Búsquedas Laborales",
      "error": "Módulo no está implementado o no carga correctamente",
      "context": null,
      "logId": "e3430661-2809-4dff-9c7f-5d57561b32f4",
      "severity": "low"
    },
    {
      "module": "terms-conditions",
      "test": "Frontend CRUD - Términos y Condiciones",
      "error": "Módulo no está implementado o no carga correctamente",
      "context": null,
      "logId": "e33c2527-cf32-4e9e-85f9-29b0942a140c",
      "severity": "low"
    },
    {
      "module": "legal",
      "test": "Frontend CRUD - Gestión Legal",
      "error": "Módulo no está implementado o no carga correctamente",
      "context": null,
      "logId": "d7f13887-2a0b-4964-a1e8-a4261144317d",
      "severity": "low"
    },
    {
      "module": "sanctions-management",
      "test": "Frontend CRUD - Gestión de Sanciones",
      "error": "Módulo no está implementado o no carga correctamente",
      "context": null,
      "logId": "d2a97671-5705-438f-a53d-f4852fbf183c",
      "severity": "low"
    },
    {
      "module": "sla-tracking",
      "test": "Frontend CRUD - Seguimiento de SLA",
      "error": "Módulo no está implementado o no carga correctamente",
      "context": null,
      "logId": "cf34e36c-86ee-410c-baa6-7c5d2045efc3",
      "severity": "low"
    },
    {
      "module": "clientes",
      "test": "Frontend CRUD - Gestión de Clientes (SIAC)",
      "error": "Módulo no está implementado o no carga correctamente",
      "context": null,
      "logId": "cf20a1e6-1e0b-45cf-8aac-6e01a712311d",
      "severity": "low"
    },
    {
      "module": "payroll-liquidation",
      "test": "Frontend CRUD - Liquidación de Sueldos",
      "error": "Módulo no está implementado o no carga correctamente",
      "context": null,
      "logId": "bfdc2d68-1205-4099-9fe4-9524ff21efb2",
      "severity": "low"
    },
    {
      "module": "audit-reports",
      "test": "Frontend CRUD - Reportes de Auditoría",
      "error": "Módulo no está implementado o no carga correctamente",
      "context": null,
      "logId": "bee8b4e0-93f1-45aa-9c89-7beeee5d4409",
      "severity": "low"
    },
    {
      "module": "real-biometric-enterprise",
      "test": "Frontend CRUD - Biometría Enterprise (Real + Verificable)",
      "error": "Módulo no está implementado o no carga correctamente",
      "context": null,
      "logId": "b3372ff8-1905-456f-bb12-4a3c54efb991",
      "severity": "low"
    },
    {
      "module": "resource-center",
      "test": "Frontend CRUD - Centro de Recursos",
      "error": "Módulo no está implementado o no carga correctamente",
      "context": null,
      "logId": "afdca232-d2cb-4a57-90c8-ee4e63ea382b",
      "severity": "low"
    },
    {
      "module": "emotional-analysis",
      "test": "Frontend CRUD - Análisis Emocional",
      "error": "Módulo no está implementado o no carga correctamente",
      "context": null,
      "logId": "aa290f66-b788-48c9-a8c6-22598ae9be7c",
      "severity": "low"
    },
    {
      "module": "visitors",
      "test": "Frontend CRUD - Control de Visitantes",
      "error": "Módulo no está implementado o no carga correctamente",
      "context": null,
      "logId": "99a348d4-d296-4e05-9653-297cac41e970",
      "severity": "low"
    },
    {
      "module": "document-management",
      "test": "Frontend CRUD - Gestión Documental",
      "error": "Módulo no está implementado o no carga correctamente",
      "context": null,
      "logId": "8edd6072-dd15-4cd0-9b4a-2c48988f2372",
      "severity": "low"
    },
    {
      "module": "biometric-consent",
      "test": "Frontend CRUD - Consentimientos Biométricos",
      "error": "Módulo no está implementado o no carga correctamente",
      "context": null,
      "logId": "84e2879e-7caa-4935-9084-407796a67389",
      "severity": "low"
    },
    {
      "module": "medical",
      "test": "Frontend CRUD - Gestión Médica",
      "error": "Módulo no está implementado o no carga correctamente",
      "context": null,
      "logId": "7efda7ae-19d0-452a-b68c-9d6eb90217a7",
      "severity": "low"
    },
    {
      "module": "vacation",
      "test": "Frontend CRUD - Gestión de Vacaciones",
      "error": "Módulo no está implementado o no carga correctamente",
      "context": null,
      "logId": "7d68f75c-b0c7-4164-9515-7e798119cf57",
      "severity": "low"
    },
    {
      "module": "professional-biometric-registration",
      "test": "Frontend CRUD - Registro Biométrico Profesional",
      "error": "Módulo no está implementado o no carga correctamente",
      "context": null,
      "logId": "7cf65c90-ea9f-44b6-89b0-2ebf9fdbb726",
      "severity": "low"
    },
    {
      "module": "kiosks-professional",
      "test": "Frontend CRUD - Gestión de Kioscos Biométricos",
      "error": "Módulo no está implementado o no carga correctamente",
      "context": null,
      "logId": "777747d0-0639-494c-b38f-95bf4589d586",
      "severity": "low"
    },
    {
      "module": "psychological-assessment",
      "test": "Frontend CRUD - Evaluación Psicológica",
      "error": "Módulo no está implementado o no carga correctamente",
      "context": null,
      "logId": "4b912f14-9ccc-4d57-ba71-4ed010d0a13d",
      "severity": "low"
    },
    {
      "module": "shifts",
      "test": "Frontend CRUD - Gestión de Turnos",
      "error": "Módulo no está implementado o no carga correctamente",
      "context": null,
      "logId": "47c4e621-fd83-41e6-9047-3cb08dbe3b6a",
      "severity": "low"
    },
    {
      "module": "notifications-enterprise",
      "test": "Frontend CRUD - Notificaciones Enterprise V3.0",
      "error": "Módulo no está implementado o no carga correctamente",
      "context": null,
      "logId": "411c458b-828b-48d8-9b7e-a126bafacb5a",
      "severity": "low"
    },
    {
      "module": "facturacion",
      "test": "Frontend CRUD - Facturación (SIAC ERP)",
      "error": "Módulo no está implementado o no carga correctamente",
      "context": null,
      "logId": "3dae5a88-a657-4bf9-afbb-edf630f9f12d",
      "severity": "low"
    },
    {
      "module": "licensing-management",
      "test": "Frontend CRUD - Gestión de Licencias",
      "error": "Módulo no está implementado o no carga correctamente",
      "context": null,
      "logId": "3c200c08-29d1-49bd-b779-9db9d2dba03a",
      "severity": "low"
    },
    {
      "module": "compliance-dashboard",
      "test": "Frontend CRUD - Dashboard de Cumplimiento",
      "error": "Módulo no está implementado o no carga correctamente",
      "context": null,
      "logId": "39a201ad-c955-440a-92cb-fe859a9209cd",
      "severity": "low"
    },
    {
      "module": "users",
      "test": "Frontend CRUD - Gestión de Usuarios",
      "error": "Módulo no está implementado o no carga correctamente",
      "context": null,
      "logId": "3969a336-a12f-4796-bdd9-e464b6da620d",
      "severity": "low"
    },
    {
      "module": "plantillas-fiscales",
      "test": "Frontend CRUD - Plantillas Fiscales",
      "error": "Módulo no está implementado o no carga correctamente",
      "context": null,
      "logId": "2e99e9b8-e149-442e-b22f-fdc4c84d0674",
      "severity": "low"
    },
    {
      "module": "access-control",
      "test": "Frontend CRUD - Control de Accesos",
      "error": "Módulo no está implementado o no carga correctamente",
      "context": null,
      "logId": "202e094a-be13-45c7-8cb9-41fd016d68da",
      "severity": "low"
    },
    {
      "module": "evaluacion-biometrica",
      "test": "Frontend CRUD - Evaluación Biométrica",
      "error": "Módulo no está implementado o no carga correctamente",
      "context": null,
      "logId": "1b246a83-afab-4621-9adf-1a7cae8f508a",
      "severity": "low"
    }
  ]
}