{
  "critical": [],
  "high": [],
  "medium": [],
  "low": [
    {
      "module": "kiosk-android",
      "test": "APK Release existe",
      "error": "APK no encontrado en build/app/outputs/flutter-apk/",
      "context": null,
      "logId": "f73e2f8c-0f25-49a1-bfaa-a3ad1ea243b8",
      "severity": "low"
    },
    {
      "module": "kiosk-android",
      "test": "Estructura proyecto Flutter",
      "error": "Faltan archivos: pubspec.yaml, lib/main.dart, android/app/build.gradle, android/app/src/main/AndroidManifest.xml",
      "context": null,
      "logId": "28fde9ab-75db-40af-b0af-4479e8072d7b",
      "severity": "low"
    },
    {
      "module": "kiosk-android",
      "test": "Endpoint móvil: GET /api/v1/users/profile",
      "error": "Server error: 500",
      "context": null,
      "logId": "2526efab-bed5-43b5-be62-116fecf655a5",
      "severity": "low"
    }
  ]
}