{
  "critical": [],
  "high": [],
  "medium": [
    {
      "module": "attendance",
      "test": "Frontend CRUD - Control de Asistencia",
      "error": "7 tests fallaron",
      "context": {
        "errors": [
          {
            "test": "Add Button",
            "error": "Botón \"Agregar Control de Asistencia\" no funciona",
            "suggestion": "Verificar onclick=\"openAddattendanceModal()\" en el HTML"
          },
          {
            "test": "CRUD - Create",
            "error": "SyntaxError: Failed to execute 'querySelector' on 'Document': 'button:contains(\"Agregar\"), button[onclick*=\"Add\"], button[onclick*=\"add\"]' is not a valid selector.",
            "suggestion": "Revisar consola del navegador para ver errores JavaScript"
          },
          {
            "test": "CRUD - Read",
            "error": "Registro con ID undefined no encontrado en la lista",
            "suggestion": "Verificar que la función loadattendance() esté poblando la tabla correctamente"
          },
          {
            "test": "CRUD - Update",
            "error": "No se encontró botón de editar",
            "suggestion": "Agregar botón con onclick=\"editattendance(id)\""
          },
          {
            "test": "CRUD - Delete",
            "error": "No se encontró botón de eliminar",
            "suggestion": "Agregar botón con onclick=\"deleteattendance(id)\""
          },
          {
            "test": "Row Buttons",
            "error": "No se encontraron botones de acción (Editar/Eliminar)",
            "suggestion": "Agregar botones en la columna de acciones con onclick=\"editattendance(id)\" y onclick=\"deleteattendance(id)\""
          },
          {
            "test": "Console Errors",
            "error": "1 errores críticos de consola detectados",
            "suggestion": "Revisar errores en consola del navegador al cargar Control de Asistencia"
          }
        ],
        "http_errors": [],
        "console_errors": [
          {
            "type": "console",
            "message": "Failed to load resource: the server responded with a status of 404 (Not Found)",
            "timestamp": "2025-10-25T17:08:57.693Z"
          }
        ],
        "network_errors": []
      },
      "logId": "6b13cc3c-2e01-416a-b59a-225160618054",
      "severity": "medium"
    }
  ],
  "low": [
    {
      "module": "sla-tracking",
      "test": "Frontend CRUD - Seguimiento de SLA",
      "error": "Módulo no está implementado o no carga correctamente",
      "context": null,
      "logId": "f1ece1ad-562b-485b-bf07-156d857751d7",
      "severity": "low"
    },
    {
      "module": "emotional-analysis",
      "test": "Frontend CRUD - Análisis Emocional",
      "error": "Módulo no está implementado o no carga correctamente",
      "context": null,
      "logId": "e42f30ad-e44a-4402-8e8c-91f76839cad0",
      "severity": "low"
    },
    {
      "module": "access-control",
      "test": "Frontend CRUD - Control de Accesos",
      "error": "Módulo no está implementado o no carga correctamente",
      "context": null,
      "logId": "d99b34e3-9887-4ff4-a842-f2512630c6cf",
      "severity": "low"
    },
    {
      "module": "document-management",
      "test": "Frontend CRUD - Gestión Documental",
      "error": "Módulo no está implementado o no carga correctamente",
      "context": null,
      "logId": "d4b6967f-b049-4ce7-9c02-616ebcac39cc",
      "severity": "low"
    },
    {
      "module": "audit-reports",
      "test": "Frontend CRUD - Reportes de Auditoría",
      "error": "Módulo no está implementado o no carga correctamente",
      "context": null,
      "logId": "ccd2a358-342b-49b6-97a8-4434c42d3d8f",
      "severity": "low"
    },
    {
      "module": "users",
      "test": "Frontend CRUD - Gestión de Usuarios",
      "error": "Módulo no está implementado o no carga correctamente",
      "context": null,
      "logId": "cb491a9d-78e8-4724-bc29-43f6e2cebf82",
      "severity": "low"
    },
    {
      "module": "sanctions-management",
      "test": "Frontend CRUD - Gestión de Sanciones",
      "error": "Módulo no está implementado o no carga correctamente",
      "context": null,
      "logId": "b88a55b5-a4af-489b-95af-7378afefefb0",
      "severity": "low"
    },
    {
      "module": "legal",
      "test": "Frontend CRUD - Gestión Legal",
      "error": "Módulo no está implementado o no carga correctamente",
      "context": null,
      "logId": "b4f88a58-e3cb-4f2d-973a-099bd04da7f4",
      "severity": "low"
    },
    {
      "module": "compliance-dashboard",
      "test": "Frontend CRUD - Dashboard de Cumplimiento",
      "error": "Módulo no está implementado o no carga correctamente",
      "context": null,
      "logId": "a93022b6-d237-4aef-a6dc-ca73cf139886",
      "severity": "low"
    },
    {
      "module": "kiosks-professional",
      "test": "Frontend CRUD - Gestión de Kioscos Biométricos",
      "error": "Módulo no está implementado o no carga correctamente",
      "context": null,
      "logId": "a03f900f-90d0-4439-9dd5-380e4455e4bd",
      "severity": "low"
    },
    {
      "module": "facturacion",
      "test": "Frontend CRUD - Facturación (SIAC ERP)",
      "error": "Módulo no está implementado o no carga correctamente",
      "context": null,
      "logId": "a02039d4-52b2-481d-b4bd-c073e1d0a5f6",
      "severity": "low"
    },
    {
      "module": "real-biometric-enterprise",
      "test": "Frontend CRUD - Biometría Enterprise (Real + Verificable)",
      "error": "Módulo no está implementado o no carga correctamente",
      "context": null,
      "logId": "91ed15e9-a0ee-423e-b546-203623e43793",
      "severity": "low"
    },
    {
      "module": "training-management",
      "test": "Frontend CRUD - Gestión de Capacitaciones",
      "error": "Módulo no está implementado o no carga correctamente",
      "context": null,
      "logId": "8e971916-40dc-4f4b-ae9d-5ec9b459b797",
      "severity": "low"
    },
    {
      "module": "clientes",
      "test": "Frontend CRUD - Gestión de Clientes (SIAC)",
      "error": "Módulo no está implementado o no carga correctamente",
      "context": null,
      "logId": "8e68d7c4-94ef-4ac7-bce4-f66c325e728e",
      "severity": "low"
    },
    {
      "module": "biometric-consent",
      "test": "Frontend CRUD - Consentimientos Biométricos",
      "error": "Módulo no está implementado o no carga correctamente",
      "context": null,
      "logId": "8a7cf962-5a97-49d2-b6fa-2fc58c54c739",
      "severity": "low"
    },
    {
      "module": "terms-conditions",
      "test": "Frontend CRUD - Términos y Condiciones",
      "error": "Módulo no está implementado o no carga correctamente",
      "context": null,
      "logId": "83b18b10-0527-4541-93c0-4e2d0816e652",
      "severity": "low"
    },
    {
      "module": "visitors",
      "test": "Frontend CRUD - Control de Visitantes",
      "error": "Módulo no está implementado o no carga correctamente",
      "context": null,
      "logId": "827ce601-9009-4d8a-b76e-70ccd09c2ba1",
      "severity": "low"
    },
    {
      "module": "medical",
      "test": "Frontend CRUD - Gestión Médica",
      "error": "Módulo no está implementado o no carga correctamente",
      "context": null,
      "logId": "7fbc9089-5b08-464d-b4cd-197189acc095",
      "severity": "low"
    },
    {
      "module": "vacation",
      "test": "Frontend CRUD - Gestión de Vacaciones",
      "error": "Módulo no está implementado o no carga correctamente",
      "context": null,
      "logId": "7323440e-e679-4736-9e0f-4b4bb88897f2",
      "severity": "low"
    },
    {
      "module": "licensing-management",
      "test": "Frontend CRUD - Gestión de Licencias",
      "error": "Módulo no está implementado o no carga correctamente",
      "context": null,
      "logId": "56bbc96b-952b-495e-95a5-e9cd1abc4011",
      "severity": "low"
    },
    {
      "module": "job-postings",
      "test": "Frontend CRUD - Búsquedas Laborales",
      "error": "Módulo no está implementado o no carga correctamente",
      "context": null,
      "logId": "4654f87e-2942-422b-a4ba-2bcf0ca219ad",
      "severity": "low"
    },
    {
      "module": "notifications-enterprise",
      "test": "Frontend CRUD - Notificaciones Enterprise V3.0",
      "error": "Módulo no está implementado o no carga correctamente",
      "context": null,
      "logId": "40767987-5172-47f3-80ab-269952698ebb",
      "severity": "low"
    },
    {
      "module": "evaluacion-biometrica",
      "test": "Frontend CRUD - Evaluación Biométrica",
      "error": "Módulo no está implementado o no carga correctamente",
      "context": null,
      "logId": "40743cac-aa18-46b2-bd28-89136421436a",
      "severity": "low"
    },
    {
      "module": "resource-center",
      "test": "Frontend CRUD - Centro de Recursos",
      "error": "Módulo no está implementado o no carga correctamente",
      "context": null,
      "logId": "2f6c4081-20de-4da2-ad9b-1b2b1f42bfbc",
      "severity": "low"
    },
    {
      "module": "professional-biometric-registration",
      "test": "Frontend CRUD - Registro Biométrico Profesional",
      "error": "Módulo no está implementado o no carga correctamente",
      "context": null,
      "logId": "275fa5ba-54c6-4b6e-a20e-1035ed932f71",
      "severity": "low"
    },
    {
      "module": "payroll-liquidation",
      "test": "Frontend CRUD - Liquidación de Sueldos",
      "error": "Módulo no está implementado o no carga correctamente",
      "context": null,
      "logId": "241e45be-1a63-40e1-8f84-804ab92e471b",
      "severity": "low"
    },
    {
      "module": "art-management",
      "test": "Frontend CRUD - Gestión de ART",
      "error": "Módulo no está implementado o no carga correctamente",
      "context": null,
      "logId": "1d64b02c-3d01-4ec0-8a50-920d2035bdfe",
      "severity": "low"
    },
    {
      "module": "employee-map",
      "test": "Frontend CRUD - Mapa de Empleados",
      "error": "Módulo no está implementado o no carga correctamente",
      "context": null,
      "logId": "12d987de-6960-47f5-a37c-3089e20844f6",
      "severity": "low"
    },
    {
      "module": "psychological-assessment",
      "test": "Frontend CRUD - Evaluación Psicológica",
      "error": "Módulo no está implementado o no carga correctamente",
      "context": null,
      "logId": "08c0418e-d1a6-421b-b4d0-ef143850a109",
      "severity": "low"
    },
    {
      "module": "plantillas-fiscales",
      "test": "Frontend CRUD - Plantillas Fiscales",
      "error": "Módulo no está implementado o no carga correctamente",
      "context": null,
      "logId": "06472bc1-2a19-4d1d-aa23-f8c3caad4789",
      "severity": "low"
    },
    {
      "module": "shifts",
      "test": "Frontend CRUD - Gestión de Turnos",
      "error": "Módulo no está implementado o no carga correctamente",
      "context": null,
      "logId": "0625da41-61ba-481c-add1-cd6908530bc5",
      "severity": "low"
    },
    {
      "module": "departments",
      "test": "Frontend CRUD - Departamentos",
      "error": "Módulo no está implementado o no carga correctamente",
      "context": null,
      "logId": "03502cc3-a7fd-413e-9fd7-5f2a87a4a609",
      "severity": "low"
    }
  ]
}