{
  "name": "search-attendance",
  "description": "Buscar attendances",
  "steps": [
    {
      "action": "navigate",
      "target": "module-attendance",
      "description": "Ir al módulo de attendances"
    },
    {
      "action": "fill",
      "target": "input-search",
      "value": "{search-term}",
      "description": "Escribir término de búsqueda"
    },
    {
      "action": "click",
      "target": "btn-search",
      "description": "Click en buscar (o Enter)"
    },
    {
      "action": "wait",
      "target": "table-attendance",
      "description": "Esperar resultados"
    },
    {
      "action": "verify",
      "target": "table-attendance",
      "contains": "{search-term}",
      "description": "Verificar resultados"
    }
  ],
  "preconditions": [
    "logged-in"
  ],
  "postconditions": [
    "results-displayed"
  ],
  "module": "attendance",
  "generatedAt": "2026-01-05T00:46:28.515Z",
  "source": "auto-generated"
}